{
  "generated_utc": "2026-04-16T06:59:04Z",
  "window": {
    "start": "2026-04-16",
    "days": 7
  },
  "days": [
    {
      "date": "2026-04-16",
      "aspects": []
    },
    {
      "date": "2026-04-17",
      "aspects": []
    },
    {
      "date": "2026-04-18",
      "aspects": []
    },
    {
      "date": "2026-04-19",
      "aspects": []
    },
    {
      "date": "2026-04-20",
      "aspects": []
    },
    {
      "date": "2026-04-21",
      "aspects": []
    },
    {
      "date": "2026-04-22",
      "aspects": []
    }
  ]
}