{
  "generated_utc": "2026-06-26T08:33:37Z",
  "window": {
    "start": "2026-06-26",
    "days": 7
  },
  "days": [
    {
      "date": "2026-06-26",
      "aspects": []
    },
    {
      "date": "2026-06-27",
      "aspects": []
    },
    {
      "date": "2026-06-28",
      "aspects": []
    },
    {
      "date": "2026-06-29",
      "aspects": []
    },
    {
      "date": "2026-06-30",
      "aspects": []
    },
    {
      "date": "2026-07-01",
      "aspects": []
    },
    {
      "date": "2026-07-02",
      "aspects": []
    }
  ]
}